KaliLinuxWangluoSaomiaoMijiZhongwenban/README.md
KaliLinuxWangluoSaomiaoMijiZhongwenban/__init__.py
KaliLinuxWangluoSaomiaoMijiZhongwenban/__main__.py
KaliLinuxWangluoSaomiaoMijiZhongwenban/file.epub
KaliLinuxWangluoSaomiaoMijiZhongwenban/index.html
KaliLinuxWangluoSaomiaoMijiZhongwenban/css/__init__.py
KaliLinuxWangluoSaomiaoMijiZhongwenban/css/annotations.css
KaliLinuxWangluoSaomiaoMijiZhongwenban/css/main.css
KaliLinuxWangluoSaomiaoMijiZhongwenban/css/normalize.css
KaliLinuxWangluoSaomiaoMijiZhongwenban/css/popup.css
KaliLinuxWangluoSaomiaoMijiZhongwenban/font/__init__.py
KaliLinuxWangluoSaomiaoMijiZhongwenban/font/fontello.eot
KaliLinuxWangluoSaomiaoMijiZhongwenban/font/fontello.svg
KaliLinuxWangluoSaomiaoMijiZhongwenban/font/fontello.ttf
KaliLinuxWangluoSaomiaoMijiZhongwenban/font/fontello.woff
KaliLinuxWangluoSaomiaoMijiZhongwenban/img/__init__.py
KaliLinuxWangluoSaomiaoMijiZhongwenban/img/annotator-glyph-sprite.png
KaliLinuxWangluoSaomiaoMijiZhongwenban/img/annotator-icon-sprite.png
KaliLinuxWangluoSaomiaoMijiZhongwenban/img/apple-touch-icon.png
KaliLinuxWangluoSaomiaoMijiZhongwenban/img/cancelfullscreen.png
KaliLinuxWangluoSaomiaoMijiZhongwenban/img/close.png
KaliLinuxWangluoSaomiaoMijiZhongwenban/img/fullscreen.png
KaliLinuxWangluoSaomiaoMijiZhongwenban/img/loader.gif
KaliLinuxWangluoSaomiaoMijiZhongwenban/img/menu-icon.png
KaliLinuxWangluoSaomiaoMijiZhongwenban/img/save.png
KaliLinuxWangluoSaomiaoMijiZhongwenban/img/saved.png
KaliLinuxWangluoSaomiaoMijiZhongwenban/img/settings-s.png
KaliLinuxWangluoSaomiaoMijiZhongwenban/img/settings.png
KaliLinuxWangluoSaomiaoMijiZhongwenban/img/star.png
KaliLinuxWangluoSaomiaoMijiZhongwenban/js/__init__.py
KaliLinuxWangluoSaomiaoMijiZhongwenban/js/epub.js
KaliLinuxWangluoSaomiaoMijiZhongwenban/js/epub.min.js
KaliLinuxWangluoSaomiaoMijiZhongwenban/js/epub.min.map
KaliLinuxWangluoSaomiaoMijiZhongwenban/js/hooks.min.js
KaliLinuxWangluoSaomiaoMijiZhongwenban/js/hooks.min.map
kali_linux_wangluo_saomiao_miji_zhongwenban-2024.3.1.0.dist-info/METADATA
kali_linux_wangluo_saomiao_miji_zhongwenban-2024.3.1.0.dist-info/WHEEL
kali_linux_wangluo_saomiao_miji_zhongwenban-2024.3.1.0.dist-info/entry_points.txt
kali_linux_wangluo_saomiao_miji_zhongwenban-2024.3.1.0.dist-info/top_level.txt
kali_linux_wangluo_saomiao_miji_zhongwenban-2024.3.1.0.dist-info/RECORD
